gym_craftingworld/__init__.py
gym_craftingworld/manual_control.py
gym_craftingworld/window.py
gym_craftingworld/envs/__init__.py
gym_craftingworld/envs/carftingworld_onehot.py
gym_craftingworld/envs/coordinates.py
gym_craftingworld/envs/crafting_world_rgb.py
gym_craftingworld/envs/craftingworld_altobs.py
gym_craftingworld/envs/craftingworld_env.py
gym_craftingworld/envs/craftingworld_env_rgb.py
gym_craftingworld/envs/craftingworld_flat.py
gym_craftingworld/envs/craftingworld_ray.py
gym_craftingworld/envs/old_crafting.py
gym_craftingworld/envs/rendering.py
tests/__init__.py
tests/craftingworld/__init__.py
tests/craftingworld/test_core.py
gym_craftingworld-0.1.9.8.dist-info/LICENSE
gym_craftingworld-0.1.9.8.dist-info/METADATA
gym_craftingworld-0.1.9.8.dist-info/WHEEL
gym_craftingworld-0.1.9.8.dist-info/top_level.txt
gym_craftingworld-0.1.9.8.dist-info/RECORD
