Metadata-Version: 2.1
Name: gym-craftingworld
Version: 0.1.9.8
Summary: A gym package for the 2d crafting multitask world
Home-page: https://github.com/lauradarcy/gym-craftingworld
Author: Laura D'Arcy
Author-email: DArcyL@cardiff.ac.uk
License: UNKNOWN
Platform: UNKNOWN
Classifier: Programming Language :: Python :: 3
Classifier: License :: OSI Approved :: MIT License
Classifier: Operating System :: OS Independent
Requires-Python: >=3.6
Requires-Dist: gym
Requires-Dist: numpy
Requires-Dist: matplotlib
Requires-Dist: pillow
